rdfdf/__init__.py
rdfdf/helpers/__init__.py
rdfdf/helpers/importers.py
rdfdf/helpers/rdfdf_utils.py
rdfdf/rdfdf.py
rdfdf/rdfdf_types.py
rdfdf-0.1.8.dist-info/LICENSE
rdfdf-0.1.8.dist-info/METADATA
rdfdf-0.1.8.dist-info/WHEEL
rdfdf-0.1.8.dist-info/RECORD
