Metadata-Version: 2.1
Name: rdfdf
Version: 0.1.8
Summary: 
License: GPL3
Author: Lukas Plank
Author-email: lupl@tuta.io
Requires-Python: >=3.10,<4.0
Classifier: License :: Other/Proprietary License
Classifier: Programming Language :: Python :: 3
Classifier: Programming Language :: Python :: 3.10
Classifier: Programming Language :: Python :: 3.11
Requires-Dist: langcodes[data] (>=3.3.0,<4.0.0)
Requires-Dist: openpyxl (>=3.1.2,<4.0.0)
Requires-Dist: pandas (>=2.0.1,<3.0.0)
Requires-Dist: rdflib (>=7.0.0,<8.0.0)
